{
  "todos": [
    {
      "id": "8360",
      "title": "adad",
      "completed": true,
      "userId": 1
    },
    {
      "id": "f8b8",
      "title": "asdsad",
      "completed": true,
      "userId": 1
    },
    {
      "id": "40b9",
      "title": "asdad",
      "completed": false,
      "userId": 1
    },
    {
      "id": "2669",
      "title": "234124214",
      "completed": false,
      "userId": 1
    }
  ],
  "users": [
    {
      "id": "1",
      "name": "Sanchir",
      "password": "test01"
    }
  ]
}